autodocz/__init__.py
autodocz/cli.py
autodocz/generator.py
autodocz/utils.py
autodocz-0.1.99.dist-info/licenses/LICENSE
autodocz-0.1.99.dist-info/METADATA
autodocz-0.1.99.dist-info/WHEEL
autodocz-0.1.99.dist-info/entry_points.txt
autodocz-0.1.99.dist-info/top_level.txt
autodocz-0.1.99.dist-info/RECORD
